[
    {
    "Firstname":"SAI",
    "Lastname":"SAGAR",
    "DOB":"08/09/1996",
    "Email":"y.saisagar@gmail.com",
    "Password":"sagarcool@96"
    },

    {
        "Firstname":"JAGGU",
        "Lastname":"MOHAN",
        "DOB":"03/06/1997",
        "Email":"jagan72@gmail.com",
        "Password":"jagan@123"
    },

    {
        "Firstname":"VENKATA",
        "Lastname":"RATNAM",
        "DOB":"21/03/1998",
        "Email":"yvratnam61@gmail.com",
        "Password":"ratnam@123"
    }
]